etc/tinydns.conf
tinydns/__init__.py
tinydns-0.0.9.dist-info/METADATA
tinydns-0.0.9.dist-info/WHEEL
tinydns-0.0.9.dist-info/entry_points.txt
tinydns-0.0.9.dist-info/top_level.txt
tinydns-0.0.9.dist-info/RECORD
