Metadata-Version: 2.1
Name: tinydns
Version: 0.0.9
Summary: this project is a tinydns automaton implementation by python
Home-page: https://github.com/xizhicode/tinydns.git
Author: zhaohengping
Author-email: 18438697706@163.com
License: UNKNOWN
Platform: UNKNOWN
Requires-Dist: gevent
Requires-Dist: dnslib
